CHANGELOG.rst
MANIFEST.in
README.rst
setup.cfg
setup.py
arsenalclientlib/__init__.py
arsenalclientlib/ec2.py
arsenalclientlib/hardware_profile.py
arsenalclientlib/node.py
arsenalclientlib/node_group.py
arsenalclientlib/operating_system.py
arsenalclientlib/settings.py
arsenalclientlib.egg-info/PKG-INFO
arsenalclientlib.egg-info/SOURCES.txt
arsenalclientlib.egg-info/dependency_links.txt
arsenalclientlib.egg-info/not-zip-safe
arsenalclientlib.egg-info/requires.txt
arsenalclientlib.egg-info/top_level.txt