Metadata-Version: 1.1
Name: arsenalclientlib
Version: 0.1
Summary: Arsenal client library
Home-page: UNKNOWN
Author: Aaron Bandt
Author-email: aaron.bandt@citygridmedia.com
License: Apache
Keywords: Arsenal devops
Platform: UNKNOWN
Classifier: Programming Language :: Python
